<?xml version="1.0" encoding="UTF-8"?>
<?xml-model href="../../Schemas/sovietrockschema1.rnc" type="application/relax-ng-compact-syntax"?>
<song>
    <details>
        <title>Голос</title>
        <artist>Владимир Кузьмин</artist>
        <year>1985</year>
        <location>Moscow</location>
        <video>https://www.youtube.com/embed/ELM9vvnTY9k</video>
    </details>
    
    <lyrics>
        <outlook>neutral</outlook>
        <verse><l>И я <self ref="memory">забуду</self>, как звучит твой голос</l>
        <l>И взгляд твой нежный в <self ref="soul">душу</self> проникает.</l>
        <l>Как вздох грyди меня приводит в трепет</l>
        <l>И <nature>льдинки</nature> <change>тают</change>, в сердце <nature>льдинки</nature> <change>тают</change>.</l>
        <l>И я забуду, как <nature>деревья</nature> <apathy-DI>плачут</apathy-DI>,</l>
        <l>И как смеются и роняют маски.</l>
        <l>И я <self ref="memory">забуду</self> осторожность ласки,</l>
        <l>И то <self ref="memory">забуду</self>, что не забывают.</l></verse>
        
        <verse><l>А ты <apathy-DI>уходишь</apathy-DI> в этот <nature>лес</nature> <change>осенний</change></l>
        <l>И на прощанье головой киваешь.</l>
        <l>Ты <apathy-DI>оставляешь радость и веселье,</apathy-DI></l>
        <l><apathy-DI>Но только голос свой не оставляешь.</apathy-DI></l>
        <l>Возьми, с собой возьми ещё полслова,</l>
        <l>Возьми пол звука, пол <nature>листа</nature>, пол <nature>ветра</nature>,</l>
        <l>Возьми полсвета, только снова, снова</l>
        <l>Мне <hope>улыбнись</hope> и не <time>дождись</time> ответа.</l></verse>
        
        <verse><l>И я <self ref="memory">забуду</self>, как звучит твой голос,</l>
        <l>Как пахнут ветки, как ласкает ветер.</l></verse>
        
        <verse><l>А <apathy-DI>ты уходишь</apathy-DI> в этот <nature>лес</nature> <change>осенний</change></l>
        <l>И на прощанье головой киваешь.</l>
        <l>Ты <apathy-DI>оставляешь радость и веселье,</apathy-DI></l>
        <l><apathy-DI>Но только голос свой не оставляешь.</apathy-DI></l>
        <l>Возьми, с собой возьми ещё полслова,</l>
        <l>Возьми пол звука, пол <nature>листа</nature>, пол ветра,</l>
        <l>Возьми полсвета, только снова, снова</l>
        <l><hope>Мне улыбнись</hope> и не <time>дождись</time> ответа.</l></verse>
        
        <verse><l>И я <self ref="memory">забуду</self>, как звучит твой голос,</l>
            <l>И я <self ref="memory">забуду</self>, как звучит твой голос,</l>
            <l>И я <self ref="memory">забуду</self>, как звучит твой голос,</l>
            <l>И я <self ref="memory">забуду</self>, как звучит твой голос.</l></verse>
        
        
    </lyrics>
</song>
